examplepy/__init__.py
examplepy/module1.py
geopro-0.1.0.dist-info/LICENSE
geopro-0.1.0.dist-info/METADATA
geopro-0.1.0.dist-info/WHEEL
geopro-0.1.0.dist-info/top_level.txt
geopro-0.1.0.dist-info/RECORD
