Metadata-Version: 2.1
Name: geopro
Version: 0.1.0
Summary: Python Geospatial Package
Home-page: https://github.com/tnmthai/geopro
Author: Thai Tran
Author-email: tnmthai@gmail.com
Project-URL: Documentation, https://github.com/tnmthai/geopro
Project-URL: Bug Reports, https://github.com/tnmthai/geopro/issues
Project-URL: Source Code, https://github.com/tnmthai/geopro
Keywords: geospatial,remote sensing,imagery
Classifier: Development Status :: 5 - Production/Stable
Classifier: Intended Audience :: Developers
Classifier: Topic :: Software Development :: Build Tools
Classifier: Programming Language :: Python :: 3
Classifier: Programming Language :: Python :: 3.6
Classifier: Programming Language :: Python :: 3.7
Classifier: Programming Language :: Python :: 3.8
Classifier: Programming Language :: Python :: 3.9
Classifier: Programming Language :: Python :: 3 :: Only
Classifier: License :: OSI Approved :: MIT License
Classifier: Operating System :: OS Independent
Requires-Python: >=3.6
License-File: LICENSE
Provides-Extra: dev
Requires-Dist: check-manifest ; extra == 'dev'
